hi_basics/__init__.py
hi_basics/__version__.py
hi_basics/app.py
hi_basics-0.0.1.dist-info/LICENSE
hi_basics-0.0.1.dist-info/METADATA
hi_basics-0.0.1.dist-info/WHEEL
hi_basics-0.0.1.dist-info/entry_points.txt
hi_basics-0.0.1.dist-info/top_level.txt
hi_basics-0.0.1.dist-info/RECORD
